LANDMarkClassifier/LANDMark.py
LANDMarkClassifier/__init__.py
LANDMarkClassifier/lm_dtree_clfs.py
LANDMarkClassifier/lm_linear_clfs.py
LANDMarkClassifier/lm_nnet_clfs.py
LANDMarkClassifier/lm_oracle_clfs.py
LANDMarkClassifier/tree.py
LANDMarkClassifier/utils.py
landmarkclassifier-2.1.2.dist-info/METADATA
landmarkclassifier-2.1.2.dist-info/WHEEL
landmarkclassifier-2.1.2.dist-info/licenses/LICENSE
landmarkclassifier-2.1.2.dist-info/RECORD
