Metadata-Version: 2.4
Name: LANDMarkClassifier
Version: 2.1.2
Summary: LANDMark: An ensemble approach to the supervised selection of biomarkers in high-throughput sequencing data
Project-URL: Homepage, https://github.com/jrudar/LANDMark
Project-URL: Repository, https://github.com/jrudar/LANDMark.git
Project-URL: Bug Tracker, https://github.com/jrudar/LANDMark/issues
Author: Teresita M. Porter, Michael Wright, G. Brian Golding
Author-email: Josip Rudar <joe.rudar@inspection.gc.ca>, Mehrdad Hajibabaei <mhajibab@uoguelph.ca>
License: MIT License
License-File: LICENSE
Keywords: classification,ecology,machine learning,multivariate statistics
Classifier: Development Status :: 5 - Production/Stable
Classifier: Intended Audience :: Science/Research
Classifier: License :: OSI Approved :: MIT License
Classifier: Natural Language :: English
Classifier: Operating System :: OS Independent
Classifier: Programming Language :: Python :: 3
Classifier: Programming Language :: Python :: 3 :: Only
Classifier: Programming Language :: Python :: 3.11
Classifier: Programming Language :: Python :: 3.12
Classifier: Programming Language :: Python :: 3.13
Requires-Python: >=3.11
Requires-Dist: joblib>=1.4.2
Requires-Dist: numpy==2.1.3
Requires-Dist: pandas>=2.2.3
Requires-Dist: scikit-learn>=1.6.1
Requires-Dist: scipy>=1.15.2
Requires-Dist: torch>=2.6.0
Provides-Extra: dev
Requires-Dist: black; extra == 'dev'
Requires-Dist: mypy; extra == 'dev'
Requires-Dist: ruff; extra == 'dev'
Requires-Dist: twine; extra == 'dev'
Provides-Extra: test
Requires-Dist: pytest; extra == 'test'
Requires-Dist: pytest-cov; extra == 'test'
